{
  "$schema": "https://json-schema.org/draft/2020-12/schema",
  "$id": "https://harp-protocol.org/schemas/harp-gateway-error.schema.json",
  "title": "Gateway Error Body",
  "type": "object",
  "required": [
    "code",
    "message"
  ],
  "properties": {
    "code": {
      "type": "string"
    },
    "message": {
      "type": "string"
    },
    "requestId": {
      "type": "string"
    },
    "details": {
      "type": "object",
      "additionalProperties": true
    }
  },
  "additionalProperties": false
}